KedaGailvTongjiJiangyiUstcGailvTongjiJiaoyanshi/README.md
KedaGailvTongjiJiangyiUstcGailvTongjiJiaoyanshi/__init__.py
KedaGailvTongjiJiangyiUstcGailvTongjiJiaoyanshi/__main__.py
KedaGailvTongjiJiangyiUstcGailvTongjiJiaoyanshi/file.pdf
KedaGailvTongjiJiangyiUstcGailvTongjiJiaoyanshi/index.html
keda_gailv_tongji_jiangyi_ustc_gailv_tongji_jiaoyanshi-2024.3.2.0.dist-info/METADATA
keda_gailv_tongji_jiangyi_ustc_gailv_tongji_jiaoyanshi-2024.3.2.0.dist-info/WHEEL
keda_gailv_tongji_jiangyi_ustc_gailv_tongji_jiaoyanshi-2024.3.2.0.dist-info/entry_points.txt
keda_gailv_tongji_jiangyi_ustc_gailv_tongji_jiaoyanshi-2024.3.2.0.dist-info/top_level.txt
keda_gailv_tongji_jiangyi_ustc_gailv_tongji_jiaoyanshi-2024.3.2.0.dist-info/RECORD
